material_plausible/__init__.py
material_plausible/plugin.py
material_plausible/templates/partials/integrations/analytics/plausible.html
material_plausible_plugin-0.3.0.dist-info/LICENSE.txt
material_plausible_plugin-0.3.0.dist-info/METADATA
material_plausible_plugin-0.3.0.dist-info/WHEEL
material_plausible_plugin-0.3.0.dist-info/entry_points.txt
material_plausible_plugin-0.3.0.dist-info/RECORD
