Metadata-Version: 2.3
Name: material-plausible-plugin
Version: 0.3.0
Summary: Plausible Analytics implementation for Material for MkDocs
License: ISC
Author: Alexander Pushkov
Author-email: alexander@notpushk.in
Requires-Python: >=3.8
Classifier: Development Status :: 5 - Production/Stable
Classifier: Environment :: Web Environment
Classifier: Framework :: MkDocs
Classifier: Programming Language :: JavaScript
Classifier: Topic :: Documentation
Classifier: Topic :: Software Development :: Documentation
Classifier: Topic :: Text Processing :: Markup :: HTML
Requires-Dist: mkdocs
Requires-Dist: mkdocs-material
Project-URL: Documentation, https://material-plausible-plugin.ale.sh/
Project-URL: Issues, https://codeberg.org/notpushkin/material-plausible-plugin/issues
Project-URL: Source, https://codeberg.org/notpushkin/material-plausible-plugin
